README.txt
setup.py
Products/__init__.py
Products.SimpleBlog.egg-info/PKG-INFO
Products.SimpleBlog.egg-info/SOURCES.txt
Products.SimpleBlog.egg-info/dependency_links.txt
Products.SimpleBlog.egg-info/namespace_packages.txt
Products.SimpleBlog.egg-info/not-zip-safe
Products.SimpleBlog.egg-info/requires.txt
Products.SimpleBlog.egg-info/top_level.txt
Products/SimpleBlog/Permissions.py
Products/SimpleBlog/SimpleBlogTool.py
Products/SimpleBlog/SimpleBlogWorkflow.py
Products/SimpleBlog/Todo.txt
Products/SimpleBlog/__init__.py
Products/SimpleBlog/config.py
Products/SimpleBlog/configure.zcml
Products/SimpleBlog/interfaces.py
Products/SimpleBlog/profiles.zcml
Products/SimpleBlog/refresh.txt
Products/SimpleBlog/releasenotes.txt
Products/SimpleBlog/tool.gif
Products/SimpleBlog/version.txt
Products/SimpleBlog/browser/__init__.py
Products/SimpleBlog/browser/configure.zcml
Products/SimpleBlog/browser/simpleblogportlet.pt
Products/SimpleBlog/browser/simpleblogportlet.py
Products/SimpleBlog/content/__init__.py
Products/SimpleBlog/content/blog.py
Products/SimpleBlog/content/blogentry.py
Products/SimpleBlog/content/blogfolder.py
Products/SimpleBlog/i18n/SimpleBlog-da.po
Products/SimpleBlog/i18n/SimpleBlog-en.po
Products/SimpleBlog/i18n/SimpleBlog-nl.po
Products/SimpleBlog/i18n/SimpleBlog-plone-da.po
Products/SimpleBlog/i18n/SimpleBlog-plone-en.po
Products/SimpleBlog/i18n/SimpleBlog-plone-nl.po
Products/SimpleBlog/i18n/SimpleBlog-plone-zh.po
Products/SimpleBlog/i18n/SimpleBlog-plone.pot
Products/SimpleBlog/i18n/SimpleBlog-zh.po
Products/SimpleBlog/i18n/SimpleBlog.pot
Products/SimpleBlog/profiles/default/actionicons.xml
Products/SimpleBlog/profiles/default/catalog.xml
Products/SimpleBlog/profiles/default/controlpanel.xml
Products/SimpleBlog/profiles/default/cssregistry.xml
Products/SimpleBlog/profiles/default/diff_tool.xml
Products/SimpleBlog/profiles/default/factorytool.xml
Products/SimpleBlog/profiles/default/metadata.xml
Products/SimpleBlog/profiles/default/portlets.xml
Products/SimpleBlog/profiles/default/propertiestool.xml
Products/SimpleBlog/profiles/default/rolemap.xml
Products/SimpleBlog/profiles/default/skins.xml
Products/SimpleBlog/profiles/default/toolset.xml
Products/SimpleBlog/profiles/default/types.xml
Products/SimpleBlog/profiles/default/workflows.xml
