Metadata-Version: 1.0
Name: Products.SimpleBlog
Version: 3.0
Summary: SimpleBlog is an easy to use Plone based weblog application.
Home-page: ttps://svn.plone.org/svn/collective/SimpleBlog/
Author: Danny Bloemendaal
Author-email: danny.bloemendaal@informaat.nl
License: GPL
Platform: UNKNOWN
Classifier: Programming Language :: Python
Classifier: Framework :: Plone
Classifier: Topic :: Software Development :: Libraries :: Python Modules
